pbscraper/__init__.py
pbscraper/common/__init__.py
pbscraper/common/utility.py
pbscraper/crawler/__init__.py
pbscraper/crawler/base_urls_crawler.py
pbscraper/crawler/books_urls_crawler.py
pbscraper/crawler/caves_urls_crawler.py
pbscraper/crawler/cite_urls_crawler.py
pbscraper/crawler/cwbook_urls_crawler.py
pbscraper/crawler/eslite_urls_crawler.py
pbscraper/crawler/kingstone_urls_crawler.py
pbscraper/crawler/kinokuniya_urls_crawler.py
pbscraper/crawler/linking_urls_crawler.py
pbscraper/crawler/momo_urls_crawler.py
pbscraper/crawler/pchome_urls_crawler.py
pbscraper/crawler/rakuten_urls_crawler.py
pbscraper/crawler/sanmin_urls_crawler.py
pbscraper/crawler/suncolor_urls_crawler.py
pbscraper/crawler/taaze_urls_crawler.py
pbscraper/crawler/tcsb_urls_crawler.py
pbscraper/crawler/tenlong_urls_crawler.py
pbscraper/crawler/udn_urls_crawler.py
pbscraper/crawler/urls_crawler_factory.py
pbscraper/crawler/yahoo_urls_crawler.py
pbscraper/parser/__init__.py
pbscraper/parser/base_parser.py
pbscraper/parser/books_parser.py
pbscraper/parser/caves_parser.py
pbscraper/parser/cite_parser.py
pbscraper/parser/cwbook_parser.py
pbscraper/parser/eslite_parser.py
pbscraper/parser/kingstone_parser.py
pbscraper/parser/linking_parser.py
pbscraper/parser/momo_parser.py
pbscraper/parser/parser_factory.py
pbscraper/parser/pchome_parser.py
pbscraper/parser/rakuten_parser.py
pbscraper/parser/sanmin_parser.py
pbscraper/parser/suncolor_parser.py
pbscraper/parser/taaze_parser.py
pbscraper/parser/tcsb_parser.py
pbscraper/parser/tenlong_parser.py
pbscraper/parser/udn_parser.py
pbscraper/parser/yahoo_parser.py
pbscraper-1.0.26.dist-info/METADATA
pbscraper-1.0.26.dist-info/WHEEL
pbscraper-1.0.26.dist-info/RECORD
