Metadata-Version: 2.1
Name: pbscraper
Version: 1.0.26
Summary: A small example package
Project-URL: Homepage, https://github.com/StevenCafe/PickBooks-Lib-Scraper
Project-URL: Bug Tracker, https://github.com/StevenCafe/PickBooks-Lib-Scraper/issues
Author-email: StevenCafe <pinylnln@google.com>
Classifier: License :: OSI Approved :: MIT License
Classifier: Operating System :: OS Independent
Classifier: Programming Language :: Python :: 3
Requires-Python: >=3.8.10
Requires-Dist: bs4
Requires-Dist: lxml
Requires-Dist: requests
